uswid/__init__.py
uswid/__init__.pyi
uswid/cli.py
uswid/cli.pyi
uswid/component.py
uswid/component.pyi
uswid/container.py
uswid/container.pyi
uswid/container_utils.py
uswid/container_utils.pyi
uswid/entity.py
uswid/entity.pyi
uswid/enums.py
uswid/enums.pyi
uswid/errors.py
uswid/errors.pyi
uswid/evidence.py
uswid/evidence.pyi
uswid/format.py
uswid/format.pyi
uswid/format_coswid.py
uswid/format_coswid.pyi
uswid/format_cyclonedx.py
uswid/format_cyclonedx.pyi
uswid/format_goswid.py
uswid/format_goswid.pyi
uswid/format_inf.py
uswid/format_inf.pyi
uswid/format_ini.py
uswid/format_ini.pyi
uswid/format_pe.py
uswid/format_pe.pyi
uswid/format_pkgconfig.py
uswid/format_pkgconfig.pyi
uswid/format_spdx.py
uswid/format_spdx.pyi
uswid/format_swid.py
uswid/format_swid.pyi
uswid/format_uswid.py
uswid/format_uswid.pyi
uswid/hash.py
uswid/hash.pyi
uswid/link.py
uswid/link.pyi
uswid/patch.py
uswid/patch.pyi
uswid/payload.py
uswid/payload.pyi
uswid/problem.py
uswid/problem.pyi
uswid/purl.py
uswid/purl.pyi
uswid/py.typed
uswid/test_uswid.py
uswid/vcs.py
uswid/vcs.pyi
uswid/vex_document.py
uswid/vex_document.pyi
uswid/vex_product.py
uswid/vex_product.pyi
uswid/vex_statement.py
uswid/vex_statement.pyi
uswid-0.5.2.dist-info/licenses/LICENSE
uswid-0.5.2.dist-info/METADATA
uswid-0.5.2.dist-info/WHEEL
uswid-0.5.2.dist-info/entry_points.txt
uswid-0.5.2.dist-info/top_level.txt
uswid-0.5.2.dist-info/RECORD
