Metadata-Version: 2.4
Name: uswid
Version: 0.5.2
Summary: A pure-python library for embedding CoSWID data
Home-page: https://github.com/hughsie/python-uswid
Author: Richard Hughes
Author-email: richard@hughsie.com
License: BSD-2-Clause-Patent
Keywords: swid,sbom,coswid
Classifier: Development Status :: 4 - Beta
Classifier: Intended Audience :: Developers
Classifier: License :: OSI Approved :: BSD License
Classifier: Programming Language :: Python :: 3
Classifier: Topic :: Utilities
Classifier: Topic :: System :: Archiving
License-File: LICENSE
Requires-Dist: cbor2
Requires-Dist: lxml
Requires-Dist: pefile
Requires-Dist: importlib-metadata>=1.0; python_version < "3.8"
Dynamic: author
Dynamic: author-email
Dynamic: classifier
Dynamic: description
Dynamic: home-page
Dynamic: keywords
Dynamic: license
Dynamic: license-file
Dynamic: requires-dist
Dynamic: summary
